jeiutils/__init__.py
jeiutils-0.3.dist-info/License
jeiutils-0.3.dist-info/METADATA
jeiutils-0.3.dist-info/WHEEL
jeiutils-0.3.dist-info/top_level.txt
jeiutils-0.3.dist-info/RECORD
