Metadata-Version: 2.1
Name: jeiutils
Version: 0.3
Summary: This is code with harry package
Home-page: UNKNOWN
Author: sergio
Author-email: UNKNOWN
License: UNKNOWN
Platform: UNKNOWN
